setup.py
distributions_ex/Binomialdistribution.py
distributions_ex/Gaussiandistribution.py
distributions_ex/Generaldistribution.py
distributions_ex/__init__.py
distributions_ex.egg-info/PKG-INFO
distributions_ex.egg-info/SOURCES.txt
distributions_ex.egg-info/dependency_links.txt
distributions_ex.egg-info/not-zip-safe
distributions_ex.egg-info/top_level.txt